random_number/__init__.py
random_number/random_number.py
random_number-0.0.3.dist-info/LICENSE
random_number-0.0.3.dist-info/METADATA
random_number-0.0.3.dist-info/WHEEL
random_number-0.0.3.dist-info/top_level.txt
random_number-0.0.3.dist-info/RECORD
